aws_ext/__init__.py
aws_ext/command_line.py
aws_ext/glue_database.py
aws_ext/glue_databases.py
aws_ext/glue_tables.py
aws_ext-0.1.0.dist-info/LICENSE
aws_ext-0.1.0.dist-info/METADATA
aws_ext-0.1.0.dist-info/WHEEL
aws_ext-0.1.0.dist-info/entry_points.txt
aws_ext-0.1.0.dist-info/top_level.txt
aws_ext-0.1.0.dist-info/RECORD
