Metadata-Version: 2.1
Name: aws-ext
Version: 0.1.0
Summary: aws_ext is a set of high level useful functions
Home-page: https://github.com/matteoredaelli/aws_ext
Author: Matteo Redaelli
Author-email: matteo.redaelli@gmail.com
License: GPL
Project-URL: Bug Tracker, https://github.com/matteoredaelli/aws_ext/issues
Classifier: Programming Language :: Python :: 3
Classifier: License :: OSI Approved :: MIT License
Classifier: Operating System :: OS Independent
Requires-Python: >=3.6
License-File: LICENSE
